hatch_conda_build/__init__.py
hatch_conda_build/_version.py
hatch_conda_build/config.py
hatch_conda_build/hooks.py
hatch_conda_build/plugin.py
hatch_conda_build-0.1.2.dist-info/METADATA
hatch_conda_build-0.1.2.dist-info/WHEEL
hatch_conda_build-0.1.2.dist-info/entry_points.txt
hatch_conda_build-0.1.2.dist-info/licenses/LICENSE
hatch_conda_build-0.1.2.dist-info/RECORD
