Metadata-Version: 2.4
Name: hatch-conda-build
Version: 0.1.2
Summary: A Hatch plugin to enable building a conda package from your pyproject.toml without having to write a separate conda build recipe meta.yaml file
License-File: LICENSE
Requires-Python: >=3.9
Requires-Dist: build
Requires-Dist: conda-souschef>=2.2.3
Requires-Dist: deepmerge
Requires-Dist: grayskull
Requires-Dist: hatchling
Requires-Dist: requests
Requires-Dist: ruamel-yaml
Provides-Extra: dev
Requires-Dist: black; extra == 'dev'
Requires-Dist: pytest; extra == 'dev'
Requires-Dist: pytest-cov; extra == 'dev'
Requires-Dist: pytest-mock; extra == 'dev'
Requires-Dist: ruff; extra == 'dev'
